Metadata-Version: 2.1
Name: glr
Version: 1.0.1
Summary: Locally run your gitlab-ci.yml scripts
Home-page: https://github.com/BeryJu/glr
Author: Jens Langhammer
Author-email: jens@beryju.org
License: MIT
Platform: UNKNOWN
Classifier: Intended Audience :: Developers
Classifier: Intended Audience :: System Administrators
Classifier: Operating System :: OS Independent
Classifier: Topic :: Software Development
